codes/booth_multiplier/booth.v
//BOOTH MULTIPLIER MODULE

module BM (input clk,
           input reset,
           input start,
           input signed [3:0] M,
           input signed [3:0] Q,
           output reg signed [7:0] product,
           output reg done);

    localparam IDLE = 2'd0;
    localparam EXECUTE = 2'd1;
    localparam SHIFT = 2'd2;
    localparam DONE = 2'd3;

    reg [1:0] state;

    reg signed [4:0] A;
    reg signed [4:0] M_reg;
    reg signed [3:0] Q_reg;
    reg Q_1;

    reg [2:0] count;
    reg signed [9:0] tempo;

    always @(posedge clk) begin

        if(reset) begin

            state <= IDLE;
            M_reg <= 5'd0;
            Q_reg <= 4'd0;
            A <= 5'd0;
            count <= 3'd0;
            Q_1 <= 1'b0;
            product <= 8'd0;
            done <= 1'd0;
        end

        else begin

            case(state) 

                IDLE: begin

                    done <= 1'b0;

                    if(start) begin

                        A <= 5'd0;
                        M_reg <= {M[3], M};
                        Q_reg <= Q;
                        Q_1 <= 1'b0;
                        count <= 3'd4;
                        product <= 8'd0;
                        state <= EXECUTE;
                    end
                end

                EXECUTE: begin

                    case({Q_reg[0], Q_1})

                        2'b00: begin

                            A <= A;
                        end

                        2'b01: begin

                            A <= A + M_reg;
                        end

                        2'b10: begin

                            A <= A - M_reg;
                        end

                        2'b11: begin

                            A <= A;
                        end
                    endcase

                    state <= SHIFT;
                end

                SHIFT: begin

                    tempo = {A, Q_reg, Q_1};
                    tempo = tempo >>> 1;

                    A <= tempo[9:5];
                    Q_reg <= tempo[4:1];
                    Q_1 <= tempo[0];

                    count <= count - 3'd1;

                    if(count == 3'd1) begin

                        state <= DONE;
                    end
                    else begin

                        state <= EXECUTE;
                    end
                end

                DONE : begin

                    product <= {A[3:0], Q_reg};
                    done <= 1'b1;
                    state <= IDLE;
                end
            endcase
        end
    end

endmodule

tb/booth_tb.v
//BOOTH MULTIPLIER TB
`timescale 1ns/1ps

module booth_test;

reg clk;
reg reset;
reg start;
reg signed [3:0] M;
reg signed [3:0] Q;

wire signed [7:0] product;
wire done;

BM uut(.clk(clk),
       .reset(reset),
       .start(start),
       .M(M),
       .Q(Q),
       .product(product),
       .done(done));
    
    always #5 clk = ~clk;

    initial begin

        $dumpfile("dump_booth.vcd");
        $dumpvars(0, booth_test);

        clk = 1'b0;
        reset = 1'b1;
        start = 1'b0;
        M = 4'd0;
        Q = 4'd0;
        #10;

        reset = 1'b0;
        M = 4'sd3;
        Q = 4'sd2;
        start = 1'b1;
        #10;

        start = 1'b0;
        #10;

        wait(done);

        $display("3 X 2");
        $display("PRODUCT: %0d", product);
        #20;

        M = -4'sd3;
        Q = 4'sd2;
        start = 1'b1;
        #10;

        start = 1'b0;
        #10;

        wait(done);

        $display("-3 X 2");
        $display("PRODUCT: %0d", product);
        #20;

        M = -4'sd4;
        Q = -4'sd2;
        start = 1'b1;
        #10;

        start = 1'b0;
        #10;

        wait(done);

        $display("-4 X -2");
        $display("PRODUCT: %0d", product);
        #20;

        M = 4'sd7;
        Q = -4'sd1;
        start = 1'b1;
        #10;

        start = 1'b0;
        #10;

        wait(done);

        $display("7 X -1");
        $display("PRODUCT: %0d", product);
        #20;

        M = -4'sd8;
        Q = 4'sd1;
        start = 1'b1;
        #10;

        start = 1'b0;
        #10;

        wait(done);

        $display("-8 X 1");
        $display("PRODUCT: %0d", product);
        #20;

        M = 4'sd7;
        Q = 4'sd7;
        start = 1'b1;
        #10;

        start = 1'b0;
        #10;

        wait(done);

        $display("7 X 7");
        $display("PRODUCT: %0d", product);
        #20;

        M = -4'sd8;
        Q = -4'sd8;
        start = 1'b1;
        #10;

        start = 1'b0;
        #10;

        wait(done);

        $display("-8 X -8");
        $display("PRODUCT: %0d", product);
        #20;

        M = 4'sd0;
        Q = 4'sd5;
        start = 1'b1;
        #10;

        start = 1'b0;
        #10;

        wait(done);

        $display("0 X 5");
        $display("PRODUCT: %0d", product);
        #20;

        M = 4'sd5;
        Q = 4'sd0;
        start = 1'b1;
        #10;

        start = 1'b0;
        #10;

        wait(done);

        $display("5 X 0");
        $display("PRODUCT: %0d", product);
        #20;

        M = -4'sd8;
        Q = 4'sd7;
        start = 1'b1;
        #10;

        start = 1'b0;
        #10;

        wait(done);

        $display("-8 X 7");
        $display("PRODUCT: %0d", product);
        #20;

        $finish;
    end

endmodule

simulation/dump_booth.vcd
$date
	Sat Jul 18 12:04:31 2026
$end
$version
	Icarus Verilog
$end
$timescale
	1ps
$end
$scope module booth_test $end
$var wire 8 ! product [7:0] $end
$var wire 1 " done $end
$var reg 4 # M [3:0] $end
$var reg 4 $ Q [3:0] $end
$var reg 1 % clk $end
$var reg 1 & reset $end
$var reg 1 ' start $end
$scope module uut $end
$var wire 4 ( M [3:0] $end
$var wire 4 ) Q [3:0] $end
$var wire 1 % clk $end
$var wire 1 & reset $end
$var wire 1 ' start $end
$var parameter 2 * DONE $end
$var parameter 2 + EXECUTE $end
$var parameter 2 , IDLE $end
$var parameter 2 - SHIFT $end
$var reg 5 . A [4:0] $end
$var reg 5 / M_reg [4:0] $end
$var reg 1 0 Q_1 $end
$var reg 4 1 Q_reg [3:0] $end
$var reg 3 2 count [2:0] $end
$var reg 1 " done $end
$var reg 8 3 product [7:0] $end
$var reg 2 4 state [1:0] $end
$var reg 10 5 tempo [9:0] $end
$upscope $end
$upscope $end
$enddefinitions $end
$comment Show the parameter values. $end
$dumpall
b10 -
b0 ,
b1 +
b11 *
$end
#0
$dumpvars
bx 5
bx 4
bx 3
bx 2
bx 1
x0
bx /
bx .
b0 )
b0 (
0'
1&
0%
b0 $
b0 #
x"
bx !
$end
#5000
0"
b0 !
b0 3
00
b0 2
b0 .
b0 1
b0 /
b0 4
1%
#10000
0%
1'
b10 $
b10 )
b11 #
b11 (
0&
#15000
b1 4
b100 2
b10 1
b11 /
1%
#20000
0%
0'
#25000
b10 4
1%
#30000
0%
#35000
b1 4
b11 2
b1 1
b10 5
1%
#40000
0%
#45000
b10 4
b11101 .
1%
#50000
0%
#55000
b1 4
b10 2
10
b1000 1
b11110 .
b1111010001 5
1%
#60000
0%
#65000
b10 4
b1 .
1%
#70000
0%
#75000
b1 4
b1 2
00
b1100 1
b0 .
b11000 5
1%
#80000
0%
#85000
b10 4
1%
#90000
0%
#95000
b11 4
b0 2
b110 1
b1100 5
1%
#100000
0%
#105000
b0 4
1"
b110 !
b110 3
1%
#110000
0%
#115000
0"
1%
#120000
0%
#125000
b1 4
b0 !
b0 3
b100 2
b10 1
b11101 /
1%
1'
b1101 #
b1101 (
#130000
0%
#135000
b10 4
1%
0'
#140000
0%
#145000
b1 4
b11 2
b1 1
b10 5
1%
#150000
0%
#155000
b10 4
b11 .
1%
#160000
0%
#165000
b1 4
b10 2
10
b1000 1
b1 .
b110001 5
1%
#170000
0%
#175000
b10 4
b11110 .
1%
#180000
0%
#185000
b1 4
b1 2
00
b100 1
b11111 .
b1111101000 5
1%
#190000
0%
#195000
b10 4
1%
#200000
0%
#205000
b11 4
b0 2
b1010 1
b1111110100 5
1%
#210000
0%
#215000
b0 4
1"
b11111010 !
b11111010 3
1%
#220000
0%
#225000
0"
1%
#230000
0%
#235000
b1 4
b0 !
b0 3
b100 2
b1110 1
b11100 /
b0 .
1%
1'
b1110 $
b1110 )
b1100 #
b1100 (
#240000
0%
#245000
b10 4
1%
0'
#250000
0%
#255000
b1 4
b11 2
b111 1
b1110 5
1%
#260000
0%
#265000
b10 4
b100 .
1%
#270000
0%
#275000
b1 4
b10 2
10
b11 1
b10 .
b1000111 5
1%
#280000
0%
#285000
b10 4
1%
#290000
0%
#295000
b1 4
b1 2
b1 1
b1 .
b100011 5
1%
#300000
0%
#305000
b10 4
1%
#310000
0%
#315000
b11 4
b0 2
b1000 1
b0 .
b10001 5
1%
#320000
0%
#325000
b0 4
1"
b1000 !
b1000 3
1%
#330000
0%
#335000
0"
1%
#340000
0%
#345000
b1 4
b0 !
b0 3
b100 2
00
b1111 1
b111 /
1%
1'
b1111 $
b1111 )
b111 #
b111 (
#350000
0%
#355000
b10 4
b11001 .
1%
0'
#360000
0%
#365000
b1 4
b11 2
10
b11100 .
b1110011111 5
1%
#370000
0%
#375000
b10 4
1%
#380000
0%
#385000
b1 4
b10 2
b111 1
b11110 .
b1111001111 5
1%
#390000
0%
#395000
b10 4
1%
#400000
0%
#405000
b1 4
b1 2
b11 1
b11111 .
b1111100111 5
1%
#410000
0%
#415000
b10 4
1%
#420000
0%
#425000
b11 4
b0 2
b1001 1
b1111110011 5
1%
#430000
0%
#435000
b0 4
1"
b11111001 !
b11111001 3
1%
#440000
0%
#445000
0"
1%
#450000
0%
#455000
b1 4
b0 !
b0 3
b100 2
00
b1 1
b11000 /
b0 .
1%
1'
b1 $
b1 )
b1000 #
b1000 (
#460000
0%
#465000
b10 4
b1000 .
1%
0'
#470000
0%
#475000
b1 4
b11 2
10
b0 1
b100 .
b10000001 5
1%
#480000
0%
#485000
b10 4
b11100 .
1%
#490000
0%
#495000
b1 4
b10 2
00
b11110 .
b1111000000 5
1%
#500000
0%
#505000
b10 4
1%
#510000
0%
#515000
b1 4
b1 2
b11111 .
b1111100000 5
1%
#520000
0%
#525000
b10 4
1%
#530000
0%
#535000
b11 4
b0 2
b1000 1
b1111110000 5
1%
#540000
0%
#545000
b0 4
1"
b11111000 !
b11111000 3
1%
#550000
0%
#555000
0"
1%
#560000
0%
#565000
b1 4
b0 !
b0 3
b100 2
b111 1
b111 /
b0 .
1%
1'
b111 $
b111 )
b111 #
b111 (
#570000
0%
#575000
b10 4
b11001 .
1%
0'
#580000
0%
#585000
b1 4
b11 2
10
b1011 1
b11100 .
b1110010111 5
1%
#590000
0%
#595000
b10 4
1%
#600000
0%
#605000
b1 4
b10 2
b101 1
b11110 .
b1111001011 5
1%
#610000
0%
#615000
b10 4
1%
#620000
0%
#625000
b1 4
b1 2
b10 1
b11111 .
b1111100101 5
1%
#630000
0%
#635000
b10 4
b110 .
1%
#640000
0%
#645000
b11 4
b0 2
00
b1 1
b11 .
b1100010 5
1%
#650000
0%
#655000
b0 4
1"
b110001 !
b110001 3
1%
#660000
0%
#665000
0"
1%
#670000
0%
#675000
b1 4
b0 !
b0 3
b100 2
b1000 1
b11000 /
b0 .
1%
1'
b1000 $
b1000 )
b1000 #
b1000 (
#680000
0%
#685000
b10 4
1%
0'
#690000
0%
#695000
b1 4
b11 2
b100 1
b1000 5
1%
#700000
0%
#705000
b10 4
1%
#710000
0%
#715000
b1 4
b10 2
b10 1
b100 5
1%
#720000
0%
#725000
b10 4
1%
#730000
0%
#735000
b1 4
b1 2
b1 1
b10 5
1%
#740000
0%
#745000
b10 4
b1000 .
1%
#750000
0%
#755000
b11 4
b0 2
10
b0 1
b100 .
b10000001 5
1%
#760000
0%
#765000
b0 4
1"
b1000000 !
b1000000 3
1%
#770000
0%
#775000
0"
1%
#780000
0%
#785000
b1 4
b0 !
b0 3
b100 2
00
b101 1
b0 /
b0 .
1%
1'
b101 $
b101 )
b0 #
b0 (
#790000
0%
#795000
b10 4
1%
0'
#800000
0%
#805000
b1 4
b11 2
10
b10 1
b101 5
1%
#810000
0%
#815000
b10 4
1%
#820000
0%
#825000
b1 4
b10 2
00
b1 1
b10 5
1%
#830000
0%
#835000
b10 4
1%
#840000
0%
#845000
b1 4
b1 2
10
b0 1
b1 5
1%
#850000
0%
#855000
b10 4
1%
#860000
0%
#865000
b11 4
b0 2
00
b0 5
1%
#870000
0%
#875000
b0 4
1"
1%
#880000
0%
#885000
0"
1%
#890000
0%
#895000
b1 4
b100 2
b101 /
1%
1'
b0 $
b0 )
b101 #
b101 (
#900000
0%
#905000
b10 4
1%
0'
#910000
0%
#915000
b1 4
b11 2
1%
#920000
0%
#925000
b10 4
1%
#930000
0%
#935000
b1 4
b10 2
1%
#940000
0%
#945000
b10 4
1%
#950000
0%
#955000
b1 4
b1 2
1%
#960000
0%
#965000
b10 4
1%
#970000
0%
#975000
b11 4
b0 2
1%
#980000
0%
#985000
b0 4
1"
1%
#990000
0%
#995000
0"
1%
#1000000
0%
#1005000
b1 4
b100 2
b111 1
b11000 /
1%
1'
b111 $
b111 )
b1000 #
b1000 (
#1010000
0%
#1015000
b10 4
b1000 .
1%
0'
#1020000
0%
#1025000
b1 4
b11 2
10
b11 1
b100 .
b10000111 5
1%
#1030000
0%
#1035000
b10 4
1%
#1040000
0%
#1045000
b1 4
b10 2
b1 1
b10 .
b1000011 5
1%
#1050000
0%
#1055000
b10 4
1%
#1060000
0%
#1065000
b1 4
b1 2
b0 1
b1 .
b100001 5
1%
#1070000
0%
#1075000
b10 4
b11001 .
1%
#1080000
0%
#1085000
b11 4
b0 2
00
b1000 1
b11100 .
b1110010000 5
1%
#1090000
0%
#1095000
b0 4
1"
b11001000 !
b11001000 3
1%
#1100000
0%
#1105000
0"
1%
