codes/pipelined_alu/pipelined_alu.v
//PIPELINED ALU MODULE

module pipe_alu(input clk,
                input reset,
                input [7:0] A,
                input [7:0] B,
                input [2:0] opcode,
                output reg [7:0] result,
                output reg carry,
                output reg zero);
    
    reg [7:0] A_reg;
    reg [7:0] B_reg;
    reg [2:0] opcode_reg;
    reg [7:0] result_reg;
    reg carry_reg;
    reg zero_reg;

    always @(posedge clk) begin

        if(reset) begin

            A_reg <= 8'd0;
            B_reg <= 8'd0;
            opcode_reg <= 3'd0;
            result_reg <= 8'd0;
            carry_reg <= 1'b0;
            zero_reg <= 1'b0;
        end

        else begin

            //STAGE 1
            A_reg <= A;
            B_reg <= B;
            opcode_reg <= opcode;

            //STAGE 2
            case(opcode_reg) 

                3'b000: begin //ADD

                    {carry_reg, result_reg} <= A_reg + B_reg;
                    zero_reg <= ((A_reg + B_reg) == 8'd0);
                end

                3'b001: begin //SUB

                    {carry_reg, result_reg} <= A_reg - B_reg;
                    zero_reg <= ((A_reg - B_reg) == 8'd0);
                end

                3'b010: begin //AND
                
                    result_reg <= A_reg & B_reg;
                    carry_reg <= 1'b0;
                    zero_reg <= ((A_reg & B_reg) == 8'd0);
                end

                3'b011: begin //OR

                    result_reg <= A_reg | B_reg;
                    carry_reg <= 1'b0;
                    zero_reg <= ((A_reg | B_reg) == 8'd0);
                end

                3'b100: begin //XOR

                    result_reg <= A_reg ^ B_reg;
                    carry_reg <= 1'b0;
                    zero_reg <= ((A_reg ^ B_reg) == 8'd0);
                end

                3'b101: begin //NOT(A)

                    result_reg <= ~A_reg;
                    carry_reg <= 1'b0;
                    zero_reg <= ((~A_reg) == 8'd0);
                end

                3'b110: begin //INC(A)

                    {carry_reg, result_reg} <= A_reg + 8'd1;
                    zero_reg <= ((A_reg + 8'd1) == 8'd0);
                end

                3'b111: begin //DEC(A)

                    {carry_reg, result_reg} <= A_reg - 8'd1;
                    zero_reg <= ((A_reg - 8'd1) == 8'd0);
                end

                default: begin

                    result_reg <= 8'd0;
                    carry_reg <= 1'b0;
                    zero_reg <= 1'b1;
                end
            endcase

            //STAGE 3
            result <= result_reg;
            carry <= carry_reg;
            zero <= zero_reg;
        
        end
    end

endmodule

tb/pipelined_alu_tb.v
//PIPELINED ALU TB

module pipe_alu_test;

reg clk;
reg reset;
reg [7:0] A;
reg [7:0] B;
reg [2:0] opcode;

wire [7:0] result;
wire carry;
wire zero;

pipe_alu DUT(.clk(clk),
               .reset(reset),
               .A(A),
               .B(B),
               .opcode(opcode),
               .result(result),
               .carry(carry),
               .zero(zero));

    always #5 clk = ~clk;

    initial begin

        $dumpfile("dump_alu.vcd");
        $dumpvars(0, pipe_alu_test);
        $monitor("TIME: %0t, A: %d, B: %d, OPCODE: %b, RESULT: %d, CARRY: %b, ZERO: %b", $time, A, B, opcode, result, carry, zero);

        clk = 1'b0;
        reset = 1'b1;
        A = 8'd0;
        B = 8'd0;
        opcode = 3'd0;
        #10;

        reset = 1'b0;
        A = 8'd20;
        B = 8'd10;
        opcode = 3'd0;
        #10;

        A = 8'd20;
        B = 8'd5;
        opcode = 3'd1;
        #10;

        A = 8'd12;
        B = 8'd10;
        opcode = 3'd2;
        #10;

        A = 8'd12;
        B = 8'd10;
        opcode = 3'd3;
        #10;

        A = 8'd12;
        B = 8'd10;
        opcode = 3'd4;
        #10;

        A = 8'd12;
        B = 8'd0;
        opcode = 3'd5;
        #10;

        A = 8'd12;
        B = 8'd0;
        opcode = 3'd6;
        #10;

        A = 8'd12;
        B = 8'd0;
        opcode = 3'd7;
        #10;

        A = 8'd255;
        B = 8'd1;
        opcode = 3'd0;
        #10;

        A = 8'd5;
        B = 8'd5;
        opcode = 3'd1;
        #10;

        A = 8'd0;
        B = 8'd0;
        opcode = 3'd0;
        #30;

        $finish;
    end

endmodule

simulation/dump_alu.vcd
$date
	Sat Jul 11 17:00:31 2026
$end
$version
	Icarus Verilog
$end
$timescale
	1s
$end
$scope module pipe_alu_test $end
$var wire 1 ! zero $end
$var wire 8 " result [7:0] $end
$var wire 1 # carry $end
$var reg 8 $ A [7:0] $end
$var reg 8 % B [7:0] $end
$var reg 1 & clk $end
$var reg 3 ' opcode [2:0] $end
$var reg 1 ( reset $end
$scope module DUT $end
$var wire 8 ) A [7:0] $end
$var wire 8 * B [7:0] $end
$var wire 1 & clk $end
$var wire 3 + opcode [2:0] $end
$var wire 1 ( reset $end
$var reg 8 , A_reg [7:0] $end
$var reg 8 - B_reg [7:0] $end
$var reg 1 # carry $end
$var reg 1 . carry_reg $end
$var reg 3 / opcode_reg [2:0] $end
$var reg 8 0 result [7:0] $end
$var reg 8 1 result_reg [7:0] $end
$var reg 1 ! zero $end
$var reg 1 2 zero_reg $end
$upscope $end
$upscope $end
$enddefinitions $end
$comment Show the parameter values. $end
$dumpall
$end
#0
$dumpvars
x2
bx 1
bx 0
bx /
x.
bx -
bx ,
b0 +
b0 *
b0 )
1(
b0 '
0&
b0 %
b0 $
x#
bx "
x!
$end
#5
02
0.
b0 1
b0 /
b0 -
b0 ,
1&
#10
0&
b1010 %
b1010 *
b10100 $
b10100 )
0(
#15
0!
0#
b0 "
b0 0
12
b1010 -
b10100 ,
1&
#20
0&
b1 '
b1 +
b101 %
b101 *
#25
1!
02
b11110 1
b1 /
b101 -
1&
#30
0&
b10 '
b10 +
b1010 %
b1010 *
b1100 $
b1100 )
#35
0!
b11110 "
b11110 0
b1111 1
b10 /
b1010 -
b1100 ,
1&
#40
0&
b11 '
b11 +
#45
b1111 "
b1111 0
b1000 1
b11 /
1&
#50
0&
b100 '
b100 +
#55
b1000 "
b1000 0
b1110 1
b100 /
1&
#60
0&
b101 '
b101 +
b0 %
b0 *
#65
b1110 "
b1110 0
b110 1
b101 /
b0 -
1&
#70
0&
b110 '
b110 +
#75
b110 "
b110 0
b11110011 1
b110 /
1&
#80
0&
b111 '
b111 +
#85
b11110011 "
b11110011 0
b1101 1
b111 /
1&
#90
0&
b0 '
b0 +
b1 %
b1 *
b11111111 $
b11111111 )
#95
b1101 "
b1101 0
b1011 1
b0 /
b1 -
b11111111 ,
1&
#100
0&
b1 '
b1 +
b101 %
b101 *
b101 $
b101 )
#105
b1011 "
b1011 0
12
1.
b0 1
b1 /
b101 -
b101 ,
1&
#110
0&
b0 '
b0 +
b0 %
b0 *
b0 $
b0 )
#115
1!
1#
b0 "
b0 0
0.
b0 /
b0 -
b0 ,
1&
#120
0&
#125
0#
1&
