codes/structural_pipelined_multiplier/struct_pipelined_multi.v
//STRUCTURED PIPELINED MULTIPLIER MODULE (5-STAGE)

module pipelined_struct_multi(input clk,
                              input reset,
                              input [7:0] A,
                              input [7:0] B,
                              output reg [15:0] product);

    reg [15:0] pp0_reg;
    reg [15:0] pp1_reg;
    reg [15:0] pp2_reg;
    reg [15:0] pp3_reg;
    reg [15:0] pp4_reg;
    reg [15:0] pp5_reg;
    reg [15:0] pp6_reg;
    reg [15:0] pp7_reg;

    reg [15:0] sum0_reg;
    reg [15:0] sum1_reg;
    reg [15:0] sum2_reg;
    reg [15:0] sum3_reg;
    reg [15:0] sum4_reg;
    reg [15:0] sum5_reg;

    reg [15:0] final_sum_reg;


    always @(posedge clk) begin

        if(reset) begin

            pp0_reg <= 16'd0;
            pp1_reg <= 16'd0;
            pp2_reg <= 16'd0;
            pp3_reg <= 16'd0;
            pp4_reg <= 16'd0;
            pp5_reg <= 16'd0;
            pp6_reg <= 16'd0;
            pp7_reg <= 16'd0;

            sum0_reg <= 16'd0;
            sum1_reg <= 16'd0;
            sum2_reg <= 16'd0;
            sum3_reg <= 16'd0;
            sum4_reg <= 16'd0;
            sum5_reg <= 16'd0;

            final_sum_reg <= 16'd0;

            product <= 16'd0;
        end

        else begin

            //STAGE 1
            pp0_reg <= (B[0]) ? {8'd0, A} : 16'd0;
            pp1_reg <= (B[1]) ? {8'd0, A}<<1 : 16'd0;
            pp2_reg <= (B[2]) ? {8'd0, A}<<2 : 16'd0;
            pp3_reg <= (B[3]) ? {8'd0, A}<<3 : 16'd0;
            pp4_reg <= (B[4]) ? {8'd0, A}<<4 : 16'd0;
            pp5_reg <= (B[5]) ? {8'd0, A}<<5 : 16'd0;
            pp6_reg <= (B[6]) ? {8'd0, A}<<6 : 16'd0;
            pp7_reg <= (B[7]) ? {8'd0, A}<<7 : 16'd0;

            //STAGE 2
            sum0_reg <= pp0_reg + pp1_reg;
            sum1_reg <= pp2_reg + pp3_reg;
            sum2_reg <= pp4_reg + pp5_reg;
            sum3_reg <= pp6_reg + pp7_reg;

            //STAGE 3
            sum4_reg <= sum0_reg + sum1_reg;
            sum5_reg <= sum2_reg + sum3_reg;

            //STAGE 4
            final_sum_reg <= sum4_reg + sum5_reg;

            //STAGE 5
            product <= final_sum_reg;        
        end
    end

endmodule

tb/struct_pipelined_multi_tb.v
//STURCTURED PIPELINED MULTIPLIER TB
`timescale 1ns/1ps

module struct_multi_test;

reg clk;
reg reset;
reg [7:0] A;
reg [7:0] B;

wire [15:0] product;

pipelined_struct_multi DUT(.clk(clk),
                           .reset(reset),
                           .A(A),
                           .B(B),
                           .product(product));
    
    always #5 clk = ~clk;

    initial begin

        $dumpfile("dump_struct_multi.vcd");
        $dumpvars(0, struct_multi_test);
        $monitor("TIME: %0t, A: %d, B: %d, PRODUCT: %d", $time, A, B, product);

        clk = 1'b0;
        reset = 1'b1;
        A = 8'd0;
        B = 8'd0;
        #10;

        reset = 1'b0;
        A = 8'd2;
        B = 8'd3;
        #10;

        A = 8'd5;
        B = 8'd4;
        #10;

        A = 8'd10;
        B = 8'd20;
        #10;

        A = 8'd20;
        B = 8'd7;
        #10;

        A = 8'd255;
        B = 8'd2;
        #10;

        A = 8'd0;
        B = 8'd0;
        #60;

        $finish;
    end

endmodule

simulation/dump_struct_multi.vcd
$date
	Sat Jul 18 12:09:09 2026
$end
$version
	Icarus Verilog
$end
$timescale
	1ps
$end
$scope module struct_multi_test $end
$var wire 16 ! product [15:0] $end
$var reg 8 " A [7:0] $end
$var reg 8 # B [7:0] $end
$var reg 1 $ clk $end
$var reg 1 % reset $end
$scope module DUT $end
$var wire 8 & A [7:0] $end
$var wire 8 ' B [7:0] $end
$var wire 1 $ clk $end
$var wire 1 % reset $end
$var reg 16 ( final_sum_reg [15:0] $end
$var reg 16 ) pp0_reg [15:0] $end
$var reg 16 * pp1_reg [15:0] $end
$var reg 16 + pp2_reg [15:0] $end
$var reg 16 , pp3_reg [15:0] $end
$var reg 16 - pp4_reg [15:0] $end
$var reg 16 . pp5_reg [15:0] $end
$var reg 16 / pp6_reg [15:0] $end
$var reg 16 0 pp7_reg [15:0] $end
$var reg 16 1 product [15:0] $end
$var reg 16 2 sum0_reg [15:0] $end
$var reg 16 3 sum1_reg [15:0] $end
$var reg 16 4 sum2_reg [15:0] $end
$var reg 16 5 sum3_reg [15:0] $end
$var reg 16 6 sum4_reg [15:0] $end
$var reg 16 7 sum5_reg [15:0] $end
$upscope $end
$upscope $end
$enddefinitions $end
$comment Show the parameter values. $end
$dumpall
$end
#0
$dumpvars
bx 7
bx 6
bx 5
bx 4
bx 3
bx 2
bx 1
bx 0
bx /
bx .
bx -
bx ,
bx +
bx *
bx )
bx (
b0 '
b0 &
1%
0$
b0 #
b0 "
bx !
$end
#5000
b0 !
b0 1
b0 (
b0 7
b0 6
b0 5
b0 4
b0 3
b0 2
b0 0
b0 /
b0 .
b0 -
b0 ,
b0 +
b0 *
b0 )
1$
#10000
0$
b11 #
b11 '
b10 "
b10 &
0%
#15000
b100 *
b10 )
1$
#20000
0$
b100 #
b100 '
b101 "
b101 &
#25000
b110 2
b10100 +
b0 *
b0 )
1$
#30000
0$
b10100 #
b10100 '
b1010 "
b1010 &
#35000
b110 6
b10100 3
b0 2
b10100000 -
b101000 +
1$
#40000
0$
b111 #
b111 '
b10100 "
b10100 &
#45000
b110 (
b10100 6
b10100000 4
b101000 3
b0 -
b1010000 +
b101000 *
b10100 )
1$
#50000
0$
b10 #
b10 '
b11111111 "
b11111111 &
#55000
b110 !
b110 1
b10100 (
b10100000 7
b101000 6
b0 4
b1010000 3
b111100 2
b0 +
b111111110 *
b0 )
1$
#60000
0$
b0 #
b0 '
b0 "
b0 &
#65000
b10100 !
b10100 1
b11001000 (
b0 7
b10001100 6
b0 3
b111111110 2
b0 *
1$
#70000
0$
#75000
b11001000 !
b11001000 1
b10001100 (
b111111110 6
b0 2
1$
#80000
0$
#85000
b10001100 !
b10001100 1
b111111110 (
b0 6
1$
#90000
0$
#95000
b111111110 !
b111111110 1
b0 (
1$
#100000
0$
#105000
b0 !
b0 1
1$
